blocoControle.v
module blocoControle (
    input inicio,
    input clk,
    input rst,
    output [1:0] M0,
    output [1:0] M1,
    output [1:0] M2,
    output LX,
    output LH, 
    output LS,
    output H,
    output pronto
);

    reg [3:0] estado;

    always @(posedge clk or rst) begin
        if (rst)
            estado <= 0;
        else begin
            if (estado == 0 && ~inicio)
                estado <= estado;
            else begin
                if (pronto)
                    estado <= estado;
                else if (estado == 8) begin
                    estado <= 0;
                end else begin
                    estado <= estado + 1;
                end
            end
        end
    end

    assign LS = estado == 4 ? 1 : estado == 6 ? 1 : estado == 7 ? 1 : 0;
    assign LX = estado == 1 ? 1 : 0;
    assign LH = estado == 3 ? 1 : estado == 5 ? 1 : 0;
    assign H = estado == 1 ? 1 : estado == 2 ? 1 : estado == 3 ? 1 : estado == 4 ? 1 : estado == 5 ? 1 : 0;
    assign M0 = estado == 4 ? 1 : estado == 5 ? 2 : estado == 7 ? 3 : 0;
    assign M1 = estado == 1 ? 1 : estado == 2 ? 1 : estado == 3 ? 1 : estado == 5 ? 1 : estado == 4 ? 3 : estado == 6 ? 3 : 0;  
    assign M2 = estado == 4 ? 1 : estado == 6 ? 2 : estado == 7 ? 2 : 0;
    assign pronto = estado == 8 ? 1 : 0;

endmodule

testbench.v
`include "blocoControle.v"

module testbench;

    reg inicio = 0;
    reg clk = 0;
    reg rst = 0;
    //reg [3:0] estado = 4'b0000; 
    wire [1:0] M0;
    wire [1:0] M1; 
    wire [1:0] M2;
    wire LX;
    wire LH;
    wire LS;
    wire H;
    wire pronto;

    blocoControle bloco1(inicio, clk, rst, M0, M1, M2, LX, LH, LS, H, pronto);

    always #1 clk <= ~clk;         

    //always #1 clk <= ~clk;

    initial begin
        $dumpvars;
        rst <= 1;
        #1;
        rst <= 0;
        inicio <= 1;
        #15;
        $finish;
    end
endmodule

dump.vcd
$date
	Wed Sep 15 20:49:41 2021
$end
$version
	Icarus Verilog
$end
$timescale
	1s
$end
$scope module testbench $end
$var wire 1 ! pronto $end
$var wire 2 " M2 [1:0] $end
$var wire 2 # M1 [1:0] $end
$var wire 2 $ M0 [1:0] $end
$var wire 1 % LX $end
$var wire 1 & LS $end
$var wire 1 ' LH $end
$var wire 1 ( H $end
$var reg 1 ) clk $end
$var reg 1 * inicio $end
$var reg 1 + rst $end
$scope module bloco1 $end
$var wire 1 ) clk $end
$var wire 1 * inicio $end
$var wire 1 + rst $end
$var wire 1 ! pronto $end
$var wire 2 , M2 [1:0] $end
$var wire 2 - M1 [1:0] $end
$var wire 2 . M0 [1:0] $end
$var wire 1 % LX $end
$var wire 1 & LS $end
$var wire 1 ' LH $end
$var wire 1 ( H $end
$var reg 4 / estado [3:0] $end
$upscope $end
$upscope $end
$enddefinitions $end
#0
$dumpvars
b0 /
b0 .
b0 -
b0 ,
1+
0*
0)
0(
0'
0&
0%
b0 $
b0 #
b0 "
0!
$end
#1
1%
1(
b1 #
b1 -
b1 /
1*
0+
1)
#2
0)
#3
0%
b10 /
1)
#4
0)
#5
1'
b11 /
1)
#6
0)
#7
b11 #
b11 -
1&
0'
b1 $
b1 .
b1 "
b1 ,
b100 /
1)
#8
0)
#9
b1 #
b1 -
1'
0&
b10 $
b10 .
b0 "
b0 ,
b101 /
1)
#10
0)
#11
0(
b11 #
b11 -
1&
0'
b0 $
b0 .
b10 "
b10 ,
b110 /
1)
#12
0)
#13
b0 #
b0 -
b11 $
b11 .
b111 /
1)
#14
0)
#15
0&
b0 $
b0 .
b0 "
b0 ,
1!
b1000 /
1)
